action_solver/__init__.py
action_solver/action.py
action_solver/factory.py
action_solver/solver.py
action_solver/state.py
action_solver-0.1.0.dist-info/licenses/LICENSE
action_solver-0.1.0.dist-info/METADATA
action_solver-0.1.0.dist-info/WHEEL
action_solver-0.1.0.dist-info/top_level.txt
action_solver-0.1.0.dist-info/zip-safe
action_solver-0.1.0.dist-info/RECORD
