Metadata-Version: 2.4
Name: action-solver
Version: 0.1.0
Summary: a library helping to structure complex code
Home-page: https://github.com/puzzleYOU/action-solver/
Author: puzzleYOU GmbH
License: MIT
Platform: any
License-File: LICENSE
Requires-Dist: igraph
Dynamic: author
Dynamic: description
Dynamic: description-content-type
Dynamic: home-page
Dynamic: license
Dynamic: license-file
Dynamic: platform
Dynamic: requires-dist
Dynamic: summary
